jenkins_update_center_helper/__init__.py
jenkins_update_center_helper/signer.py
test/__init__.py
test/test_signing.py
test/utils.py
jenkins_update_center_helper-0.1.0.dist-info/METADATA
jenkins_update_center_helper-0.1.0.dist-info/WHEEL
jenkins_update_center_helper-0.1.0.dist-info/top_level.txt
jenkins_update_center_helper-0.1.0.dist-info/RECORD
