Metadata-Version: 2.1
Name: jenkins-update-center-helper
Version: 0.1.0
Summary: helper for working with jenkins update-center.json
Home-page: https://github.com/chrahunt/python-jenkins-update-center-helper
License: MIT
Platform: UNKNOWN
Classifier: Development Status :: 3 - Alpha
Classifier: License :: OSI Approved :: MIT License
Classifier: Programming Language :: Python :: 3.6
Classifier: Programming Language :: Python :: 3.7
Requires-Python: ~=3.6
Requires-Dist: cryptography (~=2.3.1)
Provides-Extra: dev
Requires-Dist: pylint (~=2.1.1); extra == 'dev'
Requires-Dist: pytest (~=3.9.1); extra == 'dev'
Requires-Dist: twine (~=1.11.0); extra == 'dev'
Requires-Dist: wheel (~=0.32.2); extra == 'dev'
